livestock_linux/__init__.py
livestock_linux/air.py
livestock_linux/geometry.py
livestock_linux/lib_cmf.py
livestock_linux/livestock_linux.py
livestock_linux/misc.py
livestock_linux/rain.py
livestock_linux-0.0.1.dev17.dist-info/DESCRIPTION.rst
livestock_linux-0.0.1.dev17.dist-info/METADATA
livestock_linux-0.0.1.dev17.dist-info/RECORD
livestock_linux-0.0.1.dev17.dist-info/WHEEL
livestock_linux-0.0.1.dev17.dist-info/entry_points.txt
livestock_linux-0.0.1.dev17.dist-info/metadata.json
livestock_linux-0.0.1.dev17.dist-info/top_level.txt
