Metadata-Version: 2.0
Name: livestock-linux
Version: 0.0.1.dev17
Summary: Livestock is a plugin/library for Grasshopper written in Python
Home-page: https://github.com/ocni-dtu/livestock_gh
Author: Christian Kongsgaard Nielsen
Author-email: ocni@dtu.dk
License: MIT
Requires-Dist: numpy
